p115wsgidav/__init__.py
p115wsgidav/__main__.py
p115wsgidav/py.typed
p115wsgidav-0.0.3.4.dist-info/METADATA
p115wsgidav-0.0.3.4.dist-info/WHEEL
p115wsgidav-0.0.3.4.dist-info/entry_points.txt
p115wsgidav-0.0.3.4.dist-info/licenses/LICENSE
p115wsgidav-0.0.3.4.dist-info/RECORD
