Metadata-Version: 2.4
Name: p115wsgidav
Version: 0.0.3.4
Summary: Python 115 WsgiDAV
License: MIT
License-File: LICENSE
Keywords: python,115,WsgiDAV
Author: ChenyangGao
Author-email: wosiwujm@gmail.com
Requires-Python: >=3.12,<4.0
Classifier: Development Status :: 5 - Production/Stable
Classifier: Intended Audience :: Developers
Classifier: License :: OSI Approved :: MIT License
Classifier: Operating System :: OS Independent
Classifier: Programming Language :: Python
Classifier: Programming Language :: Python :: 3
Classifier: Programming Language :: Python :: 3.12
Classifier: Programming Language :: Python :: 3.13
Classifier: Programming Language :: Python :: 3.14
Classifier: Programming Language :: Python :: 3 :: Only
Classifier: Topic :: Software Development
Classifier: Topic :: Software Development :: Libraries
Classifier: Topic :: Software Development :: Libraries :: Python Modules
Requires-Dist: cachedict (>=0.0.7)
Requires-Dist: p115client (>=0.0.7.7)
Requires-Dist: pyyaml
Requires-Dist: wsgidav
Requires-Dist: yarl
Project-URL: Homepage, https://github.com/ChenyangGao/p115client/tree/main/modules/p115wsgidav
Project-URL: Repository, https://github.com/ChenyangGao/p115client/tree/main/modules/p115wsgidav
